ddddocr/__init__.py
ddddocr/common.onnx
ddddocr/common_det.onnx
ddddocr/common_old.onnx
ddddocr-1.5.6.dist-info/LICENSE
ddddocr-1.5.6.dist-info/METADATA
ddddocr-1.5.6.dist-info/WHEEL
ddddocr-1.5.6.dist-info/top_level.txt
ddddocr-1.5.6.dist-info/RECORD
