Metadata-Version: 2.1
Name: ddddocr
Version: 1.5.6
Summary: 带带弟弟OCR
Home-page: https://github.com/sml2h3/ddddocr
Author: sml2h3
Classifier: Programming Language :: Python :: 3 :: Only
Classifier: Programming Language :: Python :: 3.7
Classifier: Programming Language :: Python :: 3.8
Classifier: Programming Language :: Python :: 3.9
Classifier: Programming Language :: Python :: 3.10
Classifier: Programming Language :: Python :: 3.11
Classifier: Programming Language :: Python :: 3.12
Classifier: License :: OSI Approved :: MIT License
Classifier: Operating System :: OS Independent
Requires-Python: <3.13
License-File: LICENSE
